MANIFEST.in
README
README.rst
setup.py
PyBabel_json.egg-info/PKG-INFO
PyBabel_json.egg-info/SOURCES.txt
PyBabel_json.egg-info/dependency_links.txt
PyBabel_json.egg-info/entry_points.txt
PyBabel_json.egg-info/requires.txt
PyBabel_json.egg-info/top_level.txt
pybabel_json/__init__.py
pybabel_json/extractor.py
test/test.json