Metadata-Version: 1.0
Name: PyBabel-json
Version: 0.1.0
Summary: PyBabel json gettext strings extractor
Home-page: https://github.com/tigrawap/pybabel-json
Author: Anton Bykov aka Tigra San
Author-email: tigrawap@gmail.com
License: UNKNOWN
Platform: UNKNOWN
